flask_sqlalchemy_report/Reporter.py
flask_sqlalchemy_report/__init__.py
flask_sqlalchemy_report-0.2.4.dist-info/licenses/LICENSE.txt
flask_sqlalchemy_report-0.2.4.dist-info/METADATA
flask_sqlalchemy_report-0.2.4.dist-info/WHEEL
flask_sqlalchemy_report-0.2.4.dist-info/top_level.txt
flask_sqlalchemy_report-0.2.4.dist-info/RECORD
