Metadata-Version: 2.4
Name: flask_sqlalchemy_report
Version: 0.2.4
Summary: A useful simple to use tool to turn your sql query into a beautiful report html table
Home-page: https://github.com/birddevelper/Flask_SqlAlchemy_Report
Download-URL: https://pypi.org/project/Flask_SqlAlchemy_Report/
Author: R.E
License: GNU
Keywords: Flask,sqlAlchemy,Report,HTML,Table,SQL
License-File: LICENSE.txt
Requires-Dist: flask
Requires-Dist: flask_sqlalchemy
Dynamic: author
Dynamic: description
Dynamic: description-content-type
Dynamic: download-url
Dynamic: home-page
Dynamic: keywords
Dynamic: license
Dynamic: license-file
Dynamic: requires-dist
Dynamic: summary
